gnome_speech2text_service/__init__.py
gnome_speech2text_service/cli.py
gnome_speech2text_service/service.py
gnome_speech2text_service-1.1.0.dist-info/licenses/LICENSE
gnome_speech2text_service-1.1.0.dist-info/METADATA
gnome_speech2text_service-1.1.0.dist-info/WHEEL
gnome_speech2text_service-1.1.0.dist-info/entry_points.txt
gnome_speech2text_service-1.1.0.dist-info/top_level.txt
gnome_speech2text_service-1.1.0.dist-info/RECORD
