Metadata-Version: 2.4
Name: gnome-speech2text-service
Version: 1.1.0
Summary: D-Bus service providing speech-to-text functionality for GNOME Shell
Author-email: Kaveh Tehrani <codemonkey13x@gmail.com>
Maintainer-email: Kaveh Tehrani <codemonkey13x@gmail.com>
License-Expression: GPL-3.0-or-later
Project-URL: Homepage, https://github.com/kavehtehrani/gnome-speech2text
Project-URL: Repository, https://github.com/kavehtehrani/gnome-speech2text
Project-URL: Issues, https://github.com/kavehtehrani/gnome-speech2text/issues
Project-URL: Documentation, https://github.com/kavehtehrani/gnome-speech2text/blob/main/README.md
Keywords: gnome,speech-to-text,dbus,voice-recognition,accessibility
Classifier: Development Status :: 5 - Production/Stable
Classifier: Intended Audience :: End Users/Desktop
Classifier: Operating System :: POSIX :: Linux
Classifier: Programming Language :: Python :: 3
Classifier: Programming Language :: Python :: 3.8
Classifier: Programming Language :: Python :: 3.9
Classifier: Programming Language :: Python :: 3.10
Classifier: Programming Language :: Python :: 3.11
Classifier: Programming Language :: Python :: 3.12
Classifier: Topic :: Desktop Environment :: Gnome
Classifier: Topic :: Multimedia :: Sound/Audio :: Speech
Classifier: Topic :: Software Development :: Libraries :: Python Modules
Requires-Python: >=3.8
License-File: LICENSE
Requires-Dist: dbus-next>=0.2.3
Requires-Dist: openai-whisper>=20231117
Requires-Dist: torch>=1.13.0
Requires-Dist: torchaudio>=0.13.0
Provides-Extra: dev
Requires-Dist: build; extra == "dev"
Requires-Dist: twine; extra == "dev"
Requires-Dist: pytest; extra == "dev"
Dynamic: license-file
